GATorch/__init__.py
GATorch/ga.py
GATorch/profilers/__init__.py
GATorch/profilers/energyprofiler.py
GATorch/profilers/measurehook.py
GATorch/profilers/measurehookloss.py
GATorch/profilers/pyjoules.py
GATorch-0.0.2.dist-info/LICENSE
GATorch-0.0.2.dist-info/METADATA
GATorch-0.0.2.dist-info/WHEEL
GATorch-0.0.2.dist-info/top_level.txt
GATorch-0.0.2.dist-info/RECORD
