Metadata-Version: 2.1
Name: GATorch
Version: 0.0.2
Summary: GATorch is a tool seamlessly integrated with PyTorch that enables ML developers to generate an energy consumption report. By attaching your model, the tool automatically tracks the energy consumption of your model's training and generates graphs and plots to gain in-depth insights into the energy consumption of your model.
Author-email: Rover van der Noort <s.r.vandernoort@student.tudelft.nl>, Martijn Smits <m.j.p.smits@student.tudelft.nl>, Dajt Mullaj <d.mullaj@student.tudelft.nl>, Remy Duijsens <r.w.j.p.duijsens@student.tudelft.nl>
Project-URL: Homepage, https://github.com/GreenAITorch/GATorch
Project-URL: Bug Tracker, https://github.com/GreenAITorch/GATorch/issues
Keywords: PyTorch,Green AI,sustainable software software
Classifier: Programming Language :: Python :: 3
Classifier: License :: OSI Approved :: MIT License
Classifier: Operating System :: OS Independent
Requires-Python: >=3.7
License-File: LICENSE
Requires-Dist: torch (==2.0.0)
Requires-Dist: torchvision
Requires-Dist: torchaudio
Requires-Dist: pyRAPL
Requires-Dist: pymongo
Requires-Dist: pandas
Requires-Dist: pyJoules
Requires-Dist: pyJoules[nvidia]
Requires-Dist: matplotlib
Requires-Dist: codecarbon
Requires-Dist: scipy
Requires-Dist: tensorboard
